ratarmount/CLIHelpers.py
ratarmount/FuseMount.py
ratarmount/WriteOverlay.py
ratarmount/__init__.py
ratarmount/__main__.py
ratarmount/actions.py
ratarmount/cli.py
ratarmount/fuse.py
ratarmount/version.py
ratarmount-1.1.2.dist-info/licenses/LICENSE
ratarmount-1.1.2.dist-info/METADATA
ratarmount-1.1.2.dist-info/WHEEL
ratarmount-1.1.2.dist-info/entry_points.txt
ratarmount-1.1.2.dist-info/top_level.txt
ratarmount-1.1.2.dist-info/RECORD
