Metadata-Version: 2.4
Name: ratarmount
Version: 1.1.2
Summary: Random Access To Archived Resources
Author-email: Maximilian Knespel <mxmlnknp@gmail.com>
License: MIT
Project-URL: Homepage, https://github.com/mxmlnkn/ratarmount
Classifier: License :: OSI Approved :: MIT License
Classifier: Development Status :: 4 - Beta
Classifier: Natural Language :: English
Classifier: Operating System :: MacOS
Classifier: Operating System :: Unix
Classifier: Programming Language :: Python :: 3
Classifier: Programming Language :: Python :: 3.6
Classifier: Programming Language :: Python :: 3.7
Classifier: Programming Language :: Python :: 3.8
Classifier: Programming Language :: Python :: 3.9
Classifier: Programming Language :: Python :: 3.10
Classifier: Programming Language :: Python :: 3.11
Classifier: Programming Language :: Python :: 3.12
Classifier: Programming Language :: Python :: 3.13
Classifier: Programming Language :: Python :: 3.14
Classifier: Topic :: System :: Archiving
Classifier: Topic :: System :: Archiving :: Compression
Classifier: Topic :: System :: Filesystems
Classifier: Topic :: Utilities
Requires-Python: >=3.7
License-File: LICENSE
Requires-Dist: ratarmountcore[7z,bzip2,fat,gzip,rar,xz,zip,zstd]~=0.9.0
Requires-Dist: mfusepy~=1.0
Provides-Extra: full
Requires-Dist: ratarmountcore[full]; extra == "full"
Provides-Extra: bzip2
Requires-Dist: ratarmountcore[bzip2]; extra == "bzip2"
Provides-Extra: gzip
Requires-Dist: ratarmountcore[gzip]; extra == "gzip"
Provides-Extra: rar
Requires-Dist: ratarmountcore[rar]; extra == "rar"
Provides-Extra: xz
Requires-Dist: ratarmountcore[xz]; extra == "xz"
Provides-Extra: zip
Requires-Dist: ratarmountcore[zip]; extra == "zip"
Provides-Extra: zstd
Requires-Dist: ratarmountcore[zstd]; extra == "zstd"
Provides-Extra: squashfs
Requires-Dist: ratarmountcore[squashfs]; extra == "squashfs"
Provides-Extra: fsspec
Requires-Dist: ratarmountcore[fsspec-backends]; extra == "fsspec"
Provides-Extra: sqlar
Requires-Dist: ratarmountcore[sqlar]; extra == "sqlar"
Provides-Extra: 7z
Requires-Dist: ratarmountcore[7z]; extra == "7z"
Provides-Extra: fat
Requires-Dist: ratarmountcore[fat]; extra == "fat"
Provides-Extra: ext4
Requires-Dist: ratarmountcore[ext4]; extra == "ext4"
Provides-Extra: git
Requires-Dist: ratarmountcore[git]; extra == "git"
Dynamic: license-file
